<?xml version="1.0" encoding="UTF-8"?>
<!DOCTYPE suite SYSTEM "http://testng.org/testng-1.0.dtd">

<suite name="Complete Test Suite" verbose="1" parallel="false">
    <listeners>
        <listener class-name="com.ecom.app.BaseComponents.TestListener"/>
    </listeners>

    <test name="AllTests" preserve-order="true">
        <classes>
            <class name="com.ecom.app.Tests._01_Login_Tests"/>
            <class name="com.ecom.app.Tests._02_Product_Tests"/>
            <class name="com.ecom.app.Tests._03_Cart_Tests"/>
            <class name="com.ecom.app.Tests._04_E2E_Tests"/>
        </classes>
    </test>

</suite>

